suffix_trees/STree.py
suffix_trees/__init__.py
suffix_trees-0.3.0.dist-info/LICENSE
suffix_trees-0.3.0.dist-info/METADATA
suffix_trees-0.3.0.dist-info/WHEEL
suffix_trees-0.3.0.dist-info/top_level.txt
suffix_trees-0.3.0.dist-info/RECORD
