Metadata-Version: 1.1
Name: suffix-trees
Version: 0.3.0
Summary: Suffix trees, generalized suffix trees and string processing methods
Home-page: https://github.com/ptrus/suffix-trees
Author: Peter Us
Author-email: ptrusr@gmail.com
License: MIT
Platform: UNKNOWN
Classifier: Development Status :: 3 - Alpha
Classifier: Programming Language :: Python :: 3
Classifier: Programming Language :: Python :: 3.5
Classifier: Programming Language :: Python :: 3.6
Classifier: Programming Language :: Python :: 3.7
Classifier: Programming Language :: Python :: 3.8
